bluesky_notify/__init__.py
bluesky_notify/api/__init__.py
bluesky_notify/api/routes.py
bluesky_notify/api/server.py
bluesky_notify/cli/__init__.py
bluesky_notify/cli/commands.py
bluesky_notify/core/__init__.py
bluesky_notify/core/config.py
bluesky_notify/core/database.py
bluesky_notify/core/logger.py
bluesky_notify/core/notifier.py
bluesky_notify/core/settings.py
bluesky_notify/services/launchd/com.bluesky-notify.plist
bluesky_notify/services/systemd/bluesky-notify.service
bluesky_notify/static/app.js
bluesky_notify/static/favicon.ico
bluesky_notify/static/logo.png
bluesky_notify/static/styles.css
bluesky_notify/templates/index.html
bluesky_notify/utils/network.py
bluesky_notify-0.5.2.dist-info/LICENSE
bluesky_notify-0.5.2.dist-info/METADATA
bluesky_notify-0.5.2.dist-info/WHEEL
bluesky_notify-0.5.2.dist-info/entry_points.txt
bluesky_notify-0.5.2.dist-info/top_level.txt
bluesky_notify-0.5.2.dist-info/RECORD
