Metadata-Version: 2.1
Name: bluesky-notify
Version: 0.5.2
Summary: A cross-platform desktop notification system for Bluesky
Home-page: https://github.com/jerdog/bluesky-notify
Author: Jeremy Meiss
Author-email: Jeremy Meiss <jeremy.meiss@gmail.com>
Project-URL: Homepage, https://github.com/jerdog/bluesky-notify
Project-URL: Bug Tracker, https://github.com/jerdog/bluesky-notify/issues
Classifier: Development Status :: 5 - Production/Stable
Classifier: Intended Audience :: End Users/Desktop
Classifier: License :: OSI Approved :: MIT License
Classifier: Programming Language :: Python :: 3
Classifier: Programming Language :: Python :: 3.8
Classifier: Programming Language :: Python :: 3.9
Classifier: Programming Language :: Python :: 3.10
Classifier: Programming Language :: Python :: 3.11
Requires-Python: >=3.9
License-File: LICENSE
Requires-Dist: atproto>=0.0.56
Requires-Dist: sqlalchemy>=2.0.36
Requires-Dist: flask>=3.1.0
Requires-Dist: flask-cors>=5.0.0
Requires-Dist: flask-sqlalchemy>=3.1.1
Requires-Dist: click>=8.1.7
Requires-Dist: python-dotenv>=1.0.1
Requires-Dist: rich>=13.9.4
Requires-Dist: desktop-notifier>=3.5.0
Requires-Dist: alembic>=1.14.0
Requires-Dist: requests>=2.31.0
Requires-Dist: urllib3>=2.0.7
Requires-Dist: certifi>=2023.7.22
Requires-Dist: charset-normalizer>=3.3.2
Requires-Dist: idna>=3.4
Requires-Dist: backoff>=2.2.1
Requires-Dist: aiohttp>=3.8.0
Requires-Dist: psutil>=5.9.0
Provides-Extra: dev
Requires-Dist: pytest>=7.0.0; extra == "dev"
Requires-Dist: pytest-cov>=4.0.0; extra == "dev"
Requires-Dist: black>=22.0.0; extra == "dev"
Requires-Dist: flake8>=5.0.0; extra == "dev"
Requires-Dist: build>=1.0.0; extra == "dev"
Requires-Dist: twine>=4.0.0; extra == "dev"
